simpleSound/__init__.py
simpleSound-1.0.1.dist-info/METADATA
simpleSound-1.0.1.dist-info/WHEEL
simpleSound-1.0.1.dist-info/top_level.txt
simpleSound-1.0.1.dist-info/RECORD
